BackpackTFv2/__init__.py
BackpackTFv2/classifieds.py
BackpackTFv2/getClass.py
BackpackTFv2/postClass.py
backpacktfv2-0.0.4.dist-info/METADATA
backpacktfv2-0.0.4.dist-info/WHEEL
backpacktfv2-0.0.4.dist-info/licenses/LICENSE
backpacktfv2-0.0.4.dist-info/RECORD
