Metadata-Version: 2.3
Name: BackpackTFv2
Version: 0.0.4
Summary: Backpack TF API Library
Author: BrBriz
License-File: LICENSE
Classifier: Programming Language :: Python :: 3
Requires-Python: >=3.8
